haarpypi/__init__.py
haarpypi/main.py
haarpypi-0.3.0.dist-info/WHEEL
haarpypi-0.3.0.dist-info/METADATA
haarpypi-0.3.0.dist-info/RECORD
