Metadata-Version: 2.1
Name: haarpypi
Version: 0.3.0
Summary: haarpypi
License: MIT
Author: Yoav Kleinberger
Author-email: haarcuba@gmail.com
Requires-Python: >=3.9,<4.0
Classifier: License :: OSI Approved :: MIT License
Classifier: Programming Language :: Python :: 3
Classifier: Programming Language :: Python :: 3.9
Requires-Dist: ipython (>=7.28.0,<8.0.0)
Requires-Dist: testix (>=6.0.0,<7.0.0)
